pytrofs/__init__.py
pytrofs/trofs.py
pytrofs/tools/__init__.py
pytrofs/tools/pytrofs_util.py
pytrofs-0.1.0.dist-info/LICENSE
pytrofs-0.1.0.dist-info/METADATA
pytrofs-0.1.0.dist-info/WHEEL
pytrofs-0.1.0.dist-info/entry_points.txt
pytrofs-0.1.0.dist-info/top_level.txt
pytrofs-0.1.0.dist-info/zip-safe
pytrofs-0.1.0.dist-info/RECORD
